{
 "geoblacklight_version": "1.0",
 "dc_identifier_s": "http://data-waukeshacounty.opendata.arcgis.com/datasets/8d95e52e97f34e91a785c266511576b6_9",
 "dc_title_s": "Government Services",
 "dc_description_s": "Government buildings in Waukesha County including State, County, and Local Offices, Fire and Law Enforcement Stations, Libraries, and Post Offices.",
 "dc_rights_s": "Public",
 "dct_provenance_s": "Waukesha County",
 "layer_id_s": "",
 "layer_slug_s": "WaukeshaCounty__8d95e52e97f34e91a785c266511576b6_9",
 "layer_geom_type_s": "",
 "layer_modified_dt": "2019-04-03T18:57:02.210Z",
 "dc_format_s": "File",
 "dc_language_s": "English",
 "dct_isPartOf_sm": "Waukesha County Open Data",
 "dc_creator_sm": "Waukesha County",
 "dc_type_s": "Dataset",
 "dc_subject_sm": [
  "Government",
  "Government Facilities",
  "Libraries",
  "Post Offices",
  "State",
  "Local",
  "County",
  "Law",
  "Fire",
  "Emergency Preparedness",
  "e911"
 ],
 "dct_spatial_sm": "",
 "dct_issued_s": "2019-04-03T18:52:05.000Z",
 "dct_temporal_sm": "",
 "solr_geom": "ENVELOPE(-88.5446, -88.0623, 43.198, 42.8442)",
 "solr_year_i": "2019",
 "dct_references_s": "{\"http://schema.org/downloadUrl\":\"http://data-waukeshacounty.opendata.arcgis.com/datasets/8d95e52e97f34e91a785c266511576b6_9.geojson\",\"http://schema.org/downloadUrl\":\"http://data-waukeshacounty.opendata.arcgis.com/datasets/8d95e52e97f34e91a785c266511576b6_9.csv\",\"http://schema.org/downloadUrl\":\"http://data-waukeshacounty.opendata.arcgis.com/datasets/8d95e52e97f34e91a785c266511576b6_9.kml\",\"http://schema.org/downloadUrl\":\"http://data-waukeshacounty.opendata.arcgis.com/datasets/8d95e52e97f34e91a785c266511576b6_9.zip\",\"http://schema.org/url\":\"http://data-waukeshacounty.opendata.arcgis.com/datasets/8d95e52e97f34e91a785c266511576b6_9\"}"
}