{
 "geoblacklight_version": "1.0",
 "dc_identifier_s": "http://data-waukeshacounty.opendata.arcgis.com/datasets/fe8f50623ab341d48960be7325873d8c_1",
 "dc_title_s": "Road Centerlines Local Government",
 "dc_description_s": "Waukesha County local government road centerlines",
 "dc_rights_s": "Public",
 "dct_provenance_s": "Waukesha County",
 "layer_id_s": "",
 "layer_slug_s": "WaukeshaCounty__fe8f50623ab341d48960be7325873d8c_1",
 "layer_geom_type_s": "Polyline",
 "layer_modified_dt": "2019-04-03T17:29:40.204Z",
 "dc_format_s": "File",
 "dc_language_s": "English",
 "dct_isPartOf_sm": "Waukesha County Open Data",
 "dc_creator_sm": "Waukesha County",
 "dc_type_s": "Dataset",
 "dc_subject_sm": [
  "Centerlines",
  "streets",
  "Waukesha County",
  "WI",
  "Wisconsin",
  "Open Data"
 ],
 "dct_spatial_sm": "",
 "dct_issued_s": "2016-10-20T16:26:46.000Z",
 "dct_temporal_sm": "",
 "solr_geom": "ENVELOPE(-88.5461, -88.0589, 43.1992, 42.8359)",
 "solr_year_i": "2019",
 "dct_references_s": "{\"http://schema.org/downloadUrl\":\"http://data-waukeshacounty.opendata.arcgis.com/datasets/fe8f50623ab341d48960be7325873d8c_1.geojson\",\"http://schema.org/downloadUrl\":\"http://data-waukeshacounty.opendata.arcgis.com/datasets/fe8f50623ab341d48960be7325873d8c_1.csv\",\"http://schema.org/downloadUrl\":\"http://data-waukeshacounty.opendata.arcgis.com/datasets/fe8f50623ab341d48960be7325873d8c_1.kml\",\"http://schema.org/downloadUrl\":\"http://data-waukeshacounty.opendata.arcgis.com/datasets/fe8f50623ab341d48960be7325873d8c_1.zip\",\"http://schema.org/url\":\"http://data-waukeshacounty.opendata.arcgis.com/datasets/fe8f50623ab341d48960be7325873d8c_1\"}"
}